README.rst
setup.py
SomVarIUS/SomVarIUS
SomVarIUS/SomVarIUS_calling.c
SomVarIUS/assign_clones.py
SomVarIUS/bb_fit.py
SomVarIUS/mixture_model.py
SomVarIUS/query_muts.c
SomVarIUS.egg-info/PKG-INFO
SomVarIUS.egg-info/SOURCES.txt
SomVarIUS.egg-info/dependency_links.txt
SomVarIUS.egg-info/requires.txt
SomVarIUS.egg-info/top_level.txt