Metadata-Version: 1.1
Name: SomVarIUS
Version: 1.1
Summary: A Python utility for calling somatic mutations from a BAM or SAM file
Home-page: https://github.com/kylessmith/SomVarIUS
Author: Kyle S. Smith
Author-email: kyle.s.smith@ucdenver.edu
License: UNKNOWN
Platform: UNKNOWN
Classifier: Programming Language :: Python
